midi2hands/config.py
midi2hands/eval.py
midi2hands/main.py
midi2hands/spec.py
midi2hands/train.py
midi2hands/utils.py
midi2hands/config/discriminative_lstm.json
midi2hands/config/discriminative_transformer.json
midi2hands/config/generative_lstm.json
midi2hands/config/generative_transformer.json
midi2hands/data/test/000-Faure_ClaireDeLune_Op46No2.mid
midi2hands/data/test/001-Satie-Gymnopedie_No1.mid
midi2hands/data/test/002-Chopin-Nocturne_FDurOp15No1.mid
midi2hands/data/train/000-BachJS-FrzSuite1_AlCourSarGig.mid
midi2hands/data/train/001-Joplin_MapleLeaveRag.mid
midi2hands/data/train/002-Schulhoff-5EtudesDeJazz_No4uNo5.mid
midi2hands/data/train/003-Chopin-NocturneEsDur_Op55No2.mid
midi2hands/data/train/003-Schubert-SonateBDur_D960Satz1.mid
"midi2hands/data/train/004-Ginastera-12amerianischePreludes_1,3,4,5,10.mid"
midi2hands/data/train/004-Schumann-FantasiestueckeOp12_1.mid
midi2hands/data/train/005-Mendelssohn-LiederOhneWorte_Band1No6.mid
midi2hands/data/train/005-Schubert-ImpromptuBDur_ThemaVariation.mid
midi2hands/data/train/006-Beethoven-FuerElise.mid
midi2hands/data/train/006-Grieg-lyrStuecke_NorskOp12No6.mid
midi2hands/data/train/007-BachJS-PraeludiumCMoll_BWV999.mid
midi2hands/data/train/007-Schubert_ValseNobleAMoll_ausD969.mid
midi2hands/data/train/008-Boulez-DouzeNotations_1bis5.mid
midi2hands/data/train/008-Chopin-NocturneBMoll_No1.mid
midi2hands/data/train/009-Bach-ItalienischesKonzert.mid
midi2hands/data/train/009-BachJS-FrzSuite2_Allemande.mid
midi2hands/data/train/010-BachJS-FrzSuite2_Menuett.mid
midi2hands/data/train/010-BachJS-FrzSuite2_Sarabande.mid
midi2hands/data/train/011-Chopin-BalladeOp47No3.mid
midi2hands/data/train/011-Schubert-Serenade.mid
midi2hands/data/train/012-Mozart-ThemaVariation_FDur.mid
midi2hands/data/train/013-Clementi-Sonatine_Op36No1.mid
midi2hands/data/train/014-Schubert-SonateBDur_D960Satz2.mid
midi2hands/data/train/015-Chopin-Etude_Op25No5.mid
midi2hands/data/train/016-Beethoven-5Klavierkonzert_Satz1.mid
midi2hands-0.0.3.dist-info/LICENCE
midi2hands-0.0.3.dist-info/METADATA
midi2hands-0.0.3.dist-info/WHEEL
midi2hands-0.0.3.dist-info/entry_points.txt
midi2hands-0.0.3.dist-info/top_level.txt
midi2hands-0.0.3.dist-info/RECORD
