Metadata-Version: 2.2
Name: midi2hands
Version: 0.0.3
Summary: Training and inference for midi hand assignment.
Author-email: Oscar Andersson <oscar.966484@gmail.com>
Project-URL: Github, https://github.com/pianoviz/midi2hands
License-File: LICENCE
Requires-Dist: midiutils-python
Requires-Dist: numpy==1.26.4
Requires-Dist: onnxruntime
Provides-Extra: train
Requires-Dist: torch; extra == "train"
Requires-Dist: joblib==1.4.2; extra == "train"
Requires-Dist: matplotlib==3.9.0; extra == "train"
Requires-Dist: scikit-learn==1.5.0; extra == "train"
Requires-Dist: pandas; extra == "train"
Requires-Dist: tqdm==4.66.4; extra == "train"
Requires-Dist: onnx; extra == "train"
Requires-Dist: mlflow; extra == "train"
